defbuild/__init__.py
defbuild/bob.py
defbuild/commands.py
defbuild/versions.py
defbuild-2.1.1.dist-info/LICENSE
defbuild-2.1.1.dist-info/METADATA
defbuild-2.1.1.dist-info/WHEEL
defbuild-2.1.1.dist-info/entry_points.txt
defbuild-2.1.1.dist-info/top_level.txt
defbuild-2.1.1.dist-info/RECORD
