Metadata-Version: 2.1
Name: defbuild
Version: 2.1.1
Summary: Commandline tool for building for Defold
Home-page: UNKNOWN
Author: Mattias.Hedberg
Author-email: hedberg.a.mattias@gmail.com
License: UNKNOWN
Requires-Dist: requests
